partial_apply/__init__.py
partial_apply/partial_apply.py
partial_apply-1.0.0.dist-info/LICENSE
partial_apply-1.0.0.dist-info/METADATA
partial_apply-1.0.0.dist-info/WHEEL
partial_apply-1.0.0.dist-info/top_level.txt
partial_apply-1.0.0.dist-info/RECORD
