Metadata-Version: 2.1
Name: partial-apply
Version: 1.0.0
Summary: Partial application of functions and method names, supporting placeholder values for positional arguments.
Home-page: https://github.com/crowsonkb/partial-apply
Author: Katherine Crowson
Author-email: crowsonkb@gmail.com
License: MIT
Keywords: functional,higher-order,partial
Platform: UNKNOWN
Classifier: Development Status :: 5 - Production/Stable
Classifier: Intended Audience :: Developers
Classifier: License :: OSI Approved :: MIT License
Classifier: Operating System :: OS Independent
Classifier: Programming Language :: Python :: 2.7
Classifier: Programming Language :: Python :: 3.4
Classifier: Programming Language :: Python :: 3.5
Classifier: Programming Language :: Python :: 3.6
Classifier: Programming Language :: Python :: 3.7
Classifier: Topic :: Software Development :: Libraries :: Python Modules
Classifier: Topic :: Utilities
